ajaxcrawler
