Metadata-Version: 1.1
Name: django-ajax-crawler
Version: 0.2dev
Summary: Handle page with dynamic data.
Home-page: alex-web.ru
Author: Alexander Polesov
Author-email: alex@alex-web.ru
License: MIT License
Keywords: django crawler phantomjs
Platform: UNKNOWN
Classifier: Environment :: Web Environment
Classifier: Framework :: Django
Classifier: Intended Audience :: Developers
Classifier: License :: OSI Approved :: MIT License
Classifier: Operating System :: OS Independent
Classifier: Programming Language :: Python
Classifier: Programming Language :: Python :: 2.6
Classifier: Programming Language :: Python :: 2.7
Classifier: Topic :: Internet :: WWW/HTTP
Classifier: Topic :: Internet :: WWW/HTTP :: Dynamic Content
